funcnodes_module/__init__.py
funcnodes_module/__main__.py
funcnodes_module/_git.py
funcnodes_module/_react.py
funcnodes_module/config.py
funcnodes_module/gen_licence.py
funcnodes_module/new.py
funcnodes_module/update.py
funcnodes_module/utils.py
funcnodes_module/template_folder/.flake8
funcnodes_module/template_folder/.gitignore
funcnodes_module/template_folder/.pre-commit-config.yaml
funcnodes_module/template_folder/LICENSE
funcnodes_module/template_folder/MANIFEST.in
funcnodes_module/template_folder/README.md
funcnodes_module/template_folder/pyproject.toml
funcnodes_module/template_folder/pytest.ini
funcnodes_module/template_folder/template__.env
funcnodes_module/template_folder/.github/actions/install_package/action.yml
funcnodes_module/template_folder/.github/workflows/py_test.yml
funcnodes_module/template_folder/.github/workflows/version_publish_main.yml
funcnodes_module/template_folder/src/new_package/__init__.py
funcnodes_module/template_folder/src/react_plugin/.gitignore
funcnodes_module/template_folder/src/react_plugin/package.json
funcnodes_module/template_folder/src/react_plugin/tsconfig.json
funcnodes_module/template_folder/src/react_plugin/vite.config.ts
funcnodes_module/template_folder/src/react_plugin/src/index.tsx
funcnodes_module/template_folder/src/react_plugin/test/import.test.js
funcnodes_module/template_folder/tests/test_all_nodes_pytest.py
funcnodes_module-0.4.1.dist-info/METADATA
funcnodes_module-0.4.1.dist-info/WHEEL
funcnodes_module-0.4.1.dist-info/entry_points.txt
funcnodes_module-0.4.1.dist-info/licenses/LICENSE
funcnodes_module-0.4.1.dist-info/RECORD
