Metadata-Version: 2.4
Name: funcnodes-module
Version: 0.4.1
Author-email: Julian Kimmig <julian.kimmig@linkdlab.de>
License: MIT
License-File: LICENSE
Requires-Python: >=3.11
Requires-Dist: funcnodes>=1.0.0
Requires-Dist: licensecheck>=2024.3; python_version >= '3.11' and python_version < '4'
Requires-Dist: toml>=0.10.2
